mcp_server_mariadb/__init__.py
mcp_server_mariadb/server.py
iflow_mcp_abel9851_mcp_server_mariadb-0.1.2.dist-info/METADATA
iflow_mcp_abel9851_mcp_server_mariadb-0.1.2.dist-info/WHEEL
iflow_mcp_abel9851_mcp_server_mariadb-0.1.2.dist-info/entry_points.txt
iflow_mcp_abel9851_mcp_server_mariadb-0.1.2.dist-info/licenses/LICENSE
iflow_mcp_abel9851_mcp_server_mariadb-0.1.2.dist-info/RECORD
