Metadata-Version: 2.4
Name: iflow-mcp_abel9851_mcp-server-mariadb
Version: 0.1.2
Summary: MCP Server for MariaDB
Author-email: HeejunShin <abel9851@gmail.com>
License-File: LICENSE
Requires-Python: >=3.10
Requires-Dist: mcp[cli]>=1.3.0
Requires-Dist: mysql-connector-python>=9.2.0
Requires-Dist: pytest>=8.3.4
Requires-Dist: python-dotenv>=1.0.1
